[
  {
    "slug": "emergency-crew-volcano-eruption",
    "content": "ইমার্জেন্সি ক্রু ভলকানো ইরাপশন আপনাকে একটি ফার্স্ট রেসপন্ডার দলের ভূমিকায় অবতীর্ণ করে, যাদের কাজ হলো এক ভয়াবহ আগ্নেয়গিরির অগ্ন্যুৎপাতের সময় জীবন বাঁচানো। এই গেমটি অ্যাকশন, স্ট্র্যাটেজি এবং সিমুলেশনের সমন্বয়ে এক রোমাঞ্চকর অভিজ্ঞতা প্রদান করে।\n\nইমার্জেন্সি ক্রু ভলকানো ইরাপশন-এ, আপনাকে লাভার স্রোত, ছাইয়ের মেঘ এবং ধসে পড়া স্থাপনায় ভরা এক বিশৃঙ্খল পরিবেশে পথ চলতে হবে। আপনার লক্ষ্য হলো সাধারণ নাগরিকদের উদ্ধার করা, সম্পদ ব্যবস্থাপনা করা এবং আরও ধ্বংসযজ্ঞ রোধ করতে মুহূর্তের মধ্যে সিদ্ধান্ত নেওয়া। গেমটির বাস্তবসম্মত ফিজিক্স এবং গতিশীল ঘটনাগুলো নিশ্চিত করে যে কোনো দুটি প্লে-থ্রু একই রকম হবে না।\n\n## মূল বৈশিষ্ট্য\n\n### বাস্তবসম্মত দুর্যোগ পরিস্থিতি\nজীবন্ত ভিজ্যুয়াল এবং ফিজিক্সের মাধ্যমে আগ্নেয়গিরির অগ্ন্যুৎপাতের তীব্রতা অনুভব করুন। প্রতিটি সিদ্ধান্তই ফলাফলের উপর প্রভাব ফেলে।\n\n### দল পরিচালনা\nফায়ারফাইটার, মেডিক এবং ইঞ্জিনিয়ারসহ বিভিন্ন বিশেষজ্ঞের একটি দলকে নেতৃত্ব দিন। উদ্ধার প্রচেষ্টা সর্বোচ্চ করতে দক্ষতার সাথে কাজ বণ্টন করুন।\n\n### পরিবর্তনশীল পরিবেশ\nগেমের জগৎটি রিয়েল-টাইমে পরিবর্তিত হয়, যেখানে লাভার প্রবাহ, ভূমিকম্প এবং ধসে পড়া ভবনগুলো অপ্রত্যাশিত চ্যালেঞ্জ তৈরি করে।\n\n### সম্পদ ব্যবস্থাপনা\nআপনার দলের টিকে থাকা এবং সাফল্য নিশ্চিত করতে যানবাহন, সরঞ্জাম এবং জনবলের মতো সীমিত সম্পদের মধ্যে ভারসাম্য বজায় রাখুন।\n\n### মাল্টিপ্লেয়ার কো-অপ\nঅনলাইন কো-অপ মোডে বন্ধুদের সাথে দলবদ্ধ হয়ে একসাথে দুর্যোগ মোকাবেলা করুন এবং সর্বোচ্চ দক্ষতার জন্য কৌশল সমন্বয় করুন।\n\n## গেমপ্লের সংক্ষিপ্ত বিবরণ\nইমার্জেন্সি ক্রু ভলকানো ইরাপশন গেমটি কৌশলগত সিদ্ধান্ত গ্রহণ এবং দ্রুত প্রতিক্রিয়ার উপর আলোকপাত করে। খেলোয়াড়দের অবশ্যই উদ্ধারকাজকে অগ্রাধিকার দিতে হবে, সম্পদ বণ্টন করতে হবে এবং প্রতিনিয়ত পরিবর্তনশীল পরিস্থিতির সাথে নিজেদের মানিয়ে নিতে হবে। গেমটিতে রিয়েল-টাইম স্ট্র্যাটেজি এবং অ্যাকশন উপাদানের মিশ্রণ রয়েছে, যার জন্য খেলোয়াড়দের তাদের দলের মনোবল এবং সক্ষমতা পরিচালনা করার পাশাপাশি তাৎক্ষণিক সিদ্ধান্ত নিতে হয়। একা খেলুন বা বন্ধুদের সাথে, প্রতিটি মিশন একটি অনন্য চ্যালেঞ্জ উপস্থাপন করে যা আপনার নেতৃত্ব এবং সমস্যা সমাধানের দক্ষতা পরীক্ষা করে।",
    "frontmatter": {
      "title": "Emergency Crew Volcano Eruption",
      "description": "ইমার্জেন্সি ক্রু ভলকানো ইরাপশন একটি তীব্র অ্যাকশন-সিমুলেশন গেম, যেখানে খেলোয়াড়রা একটি আগ্নেয়গিরির দুর্যোগের সময় জীবন বাঁচাতে প্রথম সাড়াদানকারীদের একটি দলকে নেতৃত্ব দেন। এই রোমাঞ্চকর দুর্যোগ ব্যবস্থাপনা অভিজ্ঞতায় বাস্তবসম্মত চ্যালেঞ্জের মুখোমুখি হন, গুরুত্বপূর্ণ সিদ্ধান্ত নিন এবং কৌশল তৈরি করে বিজয়ের পথে এগিয়ে যান।",
      "date": "2026-04-07",
      "category": "indie",
      "image": "https://pub-c17bac2473334bf1a31be4c8877715fc.r2.dev/games/emergency-crew-volcano-eruption.webp",
      "game_name": "জরুরি কর্মীদল আগ্নেয়গিরির অগ্ন্যুৎপাত",
      "developer": "Dynamic Gaming Studios",
      "publisher": "Action Interactive",
      "release_date": "১৭ আগস্ট, ২০২১",
      "download_url": "https://pixeldrain.com/u/kp9dPrLc",
      "trailer_video_id": "",
      "genres": [
        "ক্যাজুয়াল"
      ],
      "tags": [
        "অ্যাকশন",
        "সিমুলেশন",
        "স্ট্র্যাটেজি",
        "দুর্যোগ",
        "কো-অপ"
      ],
      "platforms": [
        "Windows"
      ],
      "screenshots": [
        "https://pub-c17bac2473334bf1a31be4c8877715fc.r2.dev/games/emergency-crew-volcano-eruption-ss0.webp",
        "https://pub-c17bac2473334bf1a31be4c8877715fc.r2.dev/games/emergency-crew-volcano-eruption-ss1.webp",
        "https://pub-c17bac2473334bf1a31be4c8877715fc.r2.dev/games/emergency-crew-volcano-eruption-ss2.webp"
      ]
    }
  },
  {
    "slug": "i-wani-hug-that-gator",
    "content": "লেকসাইড হলো-তে একজন কৌতূহলী নবাগতের ভূমিকায় অবতীর্ণ হন, যেখানে আপনার লক্ষ্য খুবই সহজ: শহরের বদমেজাজি কুমিরটির সাথে বন্ধুত্ব করা। 'আই ওয়ান্স হাগ দ্যাট গেটর' একটি মজাদার সিমুলেশন গেম, যা অন্বেষণ, গল্প বলা এবং কিছুটা হাস্যরসের মিশ্রণ ঘটায়।\n\nশহরটি ঘুরে দেখার সময় আপনি গোপন রহস্য উন্মোচন করবেন, অদ্ভুত বাসিন্দাদের সাথে দেখা করবেন এবং ধীরে ধীরে সেই অধরা কুমিরটির বিশ্বাস অর্জন করবেন। এর আকর্ষণীয় পিক্সেল আর্ট শৈলী এবং আন্তরিক গল্পের মাধ্যমে, এই গেমটি আপনাকে আরাম এবং রোমাঞ্চের এক অনন্য মিশ্রণ উপহার দেবে। আপনি কি কুমিরটিকে আপনার বন্ধুত্ব—কিংবা এমনকি একটি আলিঙ্গন—গ্রহণ করতে রাজি করাতে পারবেন?\n\n## মূল বৈশিষ্ট্য\n\n### আকর্ষণীয় পিক্সেল আর্ট শৈলী\nসুন্দরভাবে তৈরি একটি পিক্সেল আর্ট জগতে নিজেকে নিমজ্জিত করুন, যা প্রাণবন্ত রঙ এবং সূক্ষ্ম বিবরণে পরিপূর্ণ, যা লেকসাইড হলো-কে জীবন্ত করে তোলে।\n\n### আকর্ষণীয় এনপিসি মিথস্ক্রিয়া\nস্মরণীয় কিছু চরিত্রের সাথে পরিচিত হন, যাদের প্রত্যেকের নিজস্ব গল্প এবং ব্যক্তিত্ব রয়েছে, যারা কুমিরটির সাথে বন্ধুত্ব করার আপনার এই যাত্রায় সাহায্য করবে বা বাধা দেবে।\n\n### ডাইনামিক ডায়ালগ সিস্টেম\nএকটি শাখা-প্রশাখা যুক্ত ডায়ালগ সিস্টেমের মাধ্যমে আপনার যাত্রাকে নিজের মতো করে সাজিয়ে নিন, যা আপনাকে শহরবাসী এবং কুমিরটির সাথে কীভাবে কথা বলবেন তা বেছে নেওয়ার সুযোগ দেবে।\n\n### আরামদায়ক অন্বেষণ\nলেকসাইড হলো-তে স্বাধীনভাবে ঘুরে বেড়ান, লুকানো জায়গা আবিষ্কার করুন, হালকা ধাঁধা সমাধান করুন এবং শহরের রহস্য উন্মোচন করুন।\n\n### আবেগঘন গল্প বলার ধরণ\nবন্ধুত্ব, বিশ্বাস এবং ভয়কে জয় করার মতো বিষয়গুলো নিয়ে তৈরি একটি হৃদয়স্পর্শী আখ্যানের অভিজ্ঞতা নিন।\n\n## গেমপ্লের সংক্ষিপ্ত বিবরণ\n\n'আই ওয়ানি হাগ দ্যাট গেটর' গেমটি অন্বেষণ এবং সম্পর্ক তৈরির উপর আলোকপাত করে। আপনি শহরবাসীদের সাথে গল্প করে, বিভিন্ন কাজ সম্পন্ন করে এবং ধীরে ধীরে কুমিরটির বিশ্বাস অর্জন করে আপনার দিন কাটাবেন। গেমটি সৃজনশীলতা এবং ধৈর্যকে উৎসাহিত করে, কারণ আপনাকে খুঁজে বের করতে হবে কীভাবে কুমিরটিকে ভয় না দেখিয়ে তার কাছে যাওয়া যায়। হালকা ধাঁধা, আকর্ষণীয় সংলাপ এবং একটি আরামদায়ক পরিবেশের মিশ্রণে, এই গেমটি সেইসব খেলোয়াড়দের জন্য উপযুক্ত যারা একটি আরামদায়ক অথচ আবেগগতভাবে তৃপ্তিদায়ক অভিজ্ঞতা খুঁজছেন।",
    "frontmatter": {
      "title": "I Wani Hug that Gator",
      "description": "আই ওয়ান্স হাগ দ্যাট গেটর'-এ একটি হৃদয়গ্রাহী সিমুলেশন অ্যাডভেঞ্চারে অংশ নিন, যেখানে আপনি একটি মনোরম হ্রদ-তীরবর্তী শহরে এক বদমেজাজি কুমিরের সাথে বন্ধুত্ব করবেন। যারা আরামদায়ক, গল্প-নির্ভর এবং মজাদার মোড়যুক্ত ইন্ডি গেম পছন্দ করেন, তাদের জন্য এটি একদম উপযুক্ত!",
      "date": "2026-04-07",
      "category": "indie",
      "image": "https://pub-c17bac2473334bf1a31be4c8877715fc.r2.dev/games/i-wani-hug-that-gator.webp",
      "game_name": "আমি ওই কুমিরটাকে জড়িয়ে ধরতে চাই।",
      "developer": "PixelHeart Studios",
      "publisher": "CozyGames Inc.",
      "release_date": "১৪ ফেব্রুয়ারী, ২০২৪",
      "download_url": "https://gofile.io/d/yx860g",
      "trailer_video_id": "",
      "genres": [
        "ক্যাজুয়াল",
        "ইন্ডি"
      ],
      "tags": [
        "ইন্ডি",
        "সিমুলেশন",
        "অ্যাডভেঞ্চার",
        "স্বাস্থ্যকর",
        "গল্প-নির্ভর"
      ],
      "platforms": [
        "Windows",
        "Mac",
        "Linux"
      ],
      "screenshots": [
        "https://pub-c17bac2473334bf1a31be4c8877715fc.r2.dev/games/i-wani-hug-that-gator-ss0.webp",
        "https://pub-c17bac2473334bf1a31be4c8877715fc.r2.dev/games/i-wani-hug-that-gator-ss1.webp",
        "https://pub-c17bac2473334bf1a31be4c8877715fc.r2.dev/games/i-wani-hug-that-gator-ss2.webp"
      ]
    }
  },
  {
    "slug": "kitchen-crisis",
    "content": "কিচেন ক্রাইসিস-এর রোমাঞ্চকর কুকিং সিমুলেশন গেমে রান্নাঘরের উত্তাপে প্রবেশ করুন, যা আপনার মাল্টিটাস্কিং এবং কৌশলগত দক্ষতার পরীক্ষা নেবে। এই বিশৃঙ্খলার মাঝে আপনি কি আপনার রেস্তোরাঁটি সুষ্ঠুভাবে চালিয়ে যেতে পারবেন?\n\nকিচেন ক্রাইসিস-এ আপনি একজন শেফ হিসেবে একটি ব্যস্ত রেস্তোরাঁ পরিচালনা করবেন, যা অপ্রত্যাশিত চ্যালেঞ্জের মুখোমুখি হয়। উপকরণের ঘাটতি থেকে শুরু করে খুঁতখুঁতে গ্রাহক পর্যন্ত, প্রতিটি দিনই একটি নতুন সংকট নিয়ে আসে। সুস্বাদু খাবার তৈরি করতে, আপনার রান্নাঘর আপগ্রেড করতে এবং আপনার রেস্তোরাঁকে বিপর্যয় থেকে বাঁচাতে একা কাজ করুন অথবা কো-অপ মোডে বন্ধুদের সাথে দলবদ্ধ হন।\n\n## মূল বৈশিষ্ট্য\n\n### গতিশীল রান্নাঘর ব্যবস্থাপনা\nব্যস্ততার সাথে তাল মিলিয়ে চলতে উপকরণ গুছিয়ে, অ্যাপ্লায়েন্স আপগ্রেড করে এবং কাজের ধারাকে অপ্টিমাইজ করে আপনার রান্নাঘর দক্ষতার সাথে পরিচালনা করুন।\n\n### বাস্তবসম্মত রান্নার কৌশল\nকাটা ও ভাজা থেকে শুরু করে প্লেটে সাজানো ও গার্নিশ করা পর্যন্ত, সঠিক রান্নার কৌশলের মাধ্যমে বিভিন্ন ধরনের রেসিপিতে দক্ষতা অর্জন করুন।\n\n### সংকটময় পরিস্থিতি\nবিদ্যুৎ বিভ্রাট, প্রতিদ্বন্দ্বী শেফ এবং খাদ্য সমালোচকদের মতো অপ্রত্যাশিত চ্যালেঞ্জের মুখোমুখি হন, যা আপনার অভিযোজন ক্ষমতা এবং সৃজনশীলতার পরীক্ষা নেবে।\n\n### কো-অপ মাল্টিপ্লেয়ার\nঅনলাইন কো-অপ মোডে বন্ধুদের সাথে দলবদ্ধ হয়ে কাজ ভাগ করে নিন, কার্যকরভাবে যোগাযোগ করুন এবং একসাথে রন্ধনশিল্পে শ্রেষ্ঠত্ব অর্জন করুন।\n\n### প্রোগ্রেসন সিস্টেম\nগেমের অগ্রগতির সাথে সাথে নতুন রেসিপি, রান্নাঘরের আপগ্রেড এবং কসমেটিক আইটেম আনলক করুন, এবং আপনার রেস্তোরাঁকে স্বতন্ত্র করে তুলতে নিজের মতো করে সাজিয়ে নিন।\n\n## গেমপ্লে ওভারভিউ\n\nকিচেন ক্রাইসিস দ্রুতগতির অ্যাকশনের সাথে কৌশলগত পরিকল্পনার সমন্বয় ঘটায়। খেলোয়াড়দের সীমিত সম্পদ ব্যবস্থাপনার পাশাপাশি উপকরণ প্রস্তুত করা, খাবার রান্না করা এবং গ্রাহকদের পরিবেশন করার মতো একাধিক কাজ একসাথে সামলাতে হয়। গেমটির অনন্য ক্রাইসিস ইভেন্টগুলো গেমপ্লেকে সতেজ ও চ্যালেঞ্জিং রাখে, যার জন্য দ্রুত চিন্তা এবং দলবদ্ধভাবে কাজ করার প্রয়োজন হয়। একা খেলুন বা বন্ধুদের সাথে, কিচেন ক্রাইসিস সৃজনশীলতা, কৌশল এবং মজার এক দারুণ মিশ্রণ প্রদান করে।",
    "frontmatter": {
      "title": "Kitchen Crisis",
      "description": "কিচেন ক্রাইসিস-এ ডুব দিন, একটি দ্রুতগতির রান্নার সিমুলেশন গেম যেখানে আপনাকে একটি বিশৃঙ্খল রান্নাঘর সামলাতে হবে, রেসিপি আয়ত্ত করতে হবে এবং আপনার রেস্তোরাঁকে বিপর্যয় থেকে বাঁচাতে হবে। কৌশল এবং দলবদ্ধ কাজের অনুরাগীদের জন্য এটি একদম উপযুক্ত!",
      "date": "2026-04-07",
      "category": "indie",
      "image": "https://pub-c17bac2473334bf1a31be4c8877715fc.r2.dev/games/kitchen-crisis.webp",
      "game_name": "রান্নাঘরের সংকট",
      "developer": "Simulate Studios",
      "publisher": "PixelPlay Games",
      "release_date": "২ এপ্রিল, ২০২৪",
      "download_url": "https://pixeldrain.com/u/U9RSMHMv",
      "trailer_video_id": "",
      "genres": [
        "ক্যাজুয়াল",
        "ইন্ডি"
      ],
      "tags": [
        "রান্না",
        "সিমুলেশন",
        "কৌশল",
        "ব্যবস্থাপনা",
        "সমবায়"
      ],
      "platforms": [
        "Windows",
        "Mac",
        "Linux"
      ],
      "screenshots": [
        "https://pub-c17bac2473334bf1a31be4c8877715fc.r2.dev/games/kitchen-crisis-ss0.webp",
        "https://pub-c17bac2473334bf1a31be4c8877715fc.r2.dev/games/kitchen-crisis-ss1.webp",
        "https://pub-c17bac2473334bf1a31be4c8877715fc.r2.dev/games/kitchen-crisis-ss2.webp"
      ]
    }
  },
  {
    "slug": "progressbar95",
    "content": "Progressbar95 রেট্রো আকর্ষণ এবং আকর্ষক গেমপ্লের এক অনন্য মিশ্রণ প্রদান করে, যা আর্কেড-ধাঁচের সিমুলেশনের ভক্তদের জন্য এটিকে একটি অবশ্য-খেলতে-হবে এমন গেমে পরিণত করেছে।\n\nএকজন ভার্চুয়াল কম্পিউটার ব্যবহারকারীর ভূমিকায় অবতীর্ণ হয়ে অতীতের বিভিন্ন অপারেটিং সিস্টেম নেভিগেট করুন। Progressbar95 রেট্রো নান্দনিকতার সরলতার সাথে আধুনিক গেমিং মেকানিক্সের সমন্বয় ঘটিয়ে এমন এক অভিজ্ঞতা তৈরি করে যা একই সাথে নস্টালজিক এবং সতেজ। গেমটি খেলোয়াড়দের সিস্টেম রিসোর্স ব্যবস্থাপনার পাশাপাশি বিভিন্ন কাজ সম্পন্ন করার চ্যালেঞ্জ দেয়, যা একটি দৃষ্টিনন্দন রেট্রো ডিজাইনের আবরণে মোড়ানো।\n\n## মূল বৈশিষ্ট্য\n\n### রেট্রো নান্দনিকতা\nক্লাসিক অপারেটিং সিস্টেমের পিক্সেল-পারফেক্ট পুনর্নির্মাণে নিজেকে নিমজ্জিত করুন, যা খাঁটি ভিজ্যুয়াল এবং সাউন্ড এফেক্ট দ্বারা পরিপূর্ণ।\n\n### প্রগতিশীল চ্যালেঞ্জ\nগেমটি যত এগোবে, তত নতুন লেভেল এবং অপারেটিং সিস্টেম আনলক হবে, যার প্রতিটির নিজস্ব অনন্য মেকানিক্স এবং কাজ রয়েছে।\n\n### রিসোর্স ম্যানেজমেন্ট\nআপনার ভার্চুয়াল মেশিনটি মসৃণভাবে চালু রাখতে মেমরি এবং সিপিইউ ব্যবহারের মতো সিস্টেম রিসোর্সগুলোর মধ্যে ভারসাম্য বজায় রাখুন।\n\n### মিনি-গেমস\nবিভিন্ন ধরনের মিনি-গেম উপভোগ করুন যা মূল গেমপ্লে অভিজ্ঞতায় গভীরতা এবং বৈচিত্র্য যোগ করে।\n\n### কাস্টমাইজেশন\nওয়ালপেপার, আইকন এবং অন্যান্য রেট্রো-থিমযুক্ত উপাদান দিয়ে আপনার ভার্চুয়াল ডেস্কটপকে নিজের মতো করে সাজিয়ে নিন।\n\n## গেমপ্লে ওভারভিউ\n\nProgressbar95 খেলা শুরু করা সহজ, কিন্তু একবার শুরু করলে শেষ না করে ওঠা কঠিন। খেলোয়াড়দের একটি সিমুলেটেড অপারেটিং সিস্টেমের মধ্যে বিভিন্ন কাজ সম্পন্ন করতে হয় এবং ক্র্যাশ ও স্লোডাউন এড়াতে রিসোর্স পরিচালনা করতে হয়। গেমের প্রোগ্রেসন সিস্টেমটি খেলার অগ্রগতির সাথে সাথে নতুন নতুন চ্যালেঞ্জ এবং মেকানিক্স নিয়ে আসে, যা অভিজ্ঞতাকে সতেজ ও আকর্ষণীয় রাখে। আর্কেড অ্যাকশন এবং সিমুলেশন উপাদানের মিশ্রণে Progressbar95 একটি অনন্য গেমপ্লে অভিজ্ঞতা প্রদান করে যা সাধারণ এবং হার্ডকোর উভয় ধরনের গেমারদেরই আকর্ষণ করে।",
    "frontmatter": {
      "title": "Progressbar95",
      "description": "Progressbar95 হলো একটি স্মৃতি জাগানিয়া আর্কেড সিমুলেশন গেম, যা রেট্রো নান্দনিকতার সাথে আধুনিক গেমপ্লের মেলবন্ধন ঘটায়। মজাদার ও দ্রুতগতির চ্যালেঞ্জে অংশ নেওয়ার পাশাপাশি অপারেটিং সিস্টেমের বিবর্তনের অভিজ্ঞতা লাভ করুন। সাধারণ গেমার এবং প্রযুক্তিপ্রেমী, উভয়ের জন্যই এটি উপযুক্ত।",
      "date": "2026-04-07",
      "category": "indie",
      "image": "https://pub-c17bac2473334bf1a31be4c8877715fc.r2.dev/games/progressbar95.webp",
      "game_name": "প্রোগ্রেসবার৯৫",
      "developer": "IcoFX",
      "publisher": "IcoFX",
      "release_date": "৮ সেপ্টেম্বর, ২০২০",
      "download_url": "https://pixeldrain.com/u/ujzvvxws",
      "trailer_video_id": "",
      "genres": [
        "ক্যাজুয়াল",
        "ইন্ডি",
        "সিমুলেশন"
      ],
      "tags": [
        "রেট্রো",
        "আর্কেড",
        "নস্টালজিয়া",
        "ক্যাজুয়াল",
        "সিমুলেশন"
      ],
      "platforms": [
        "Windows"
      ],
      "screenshots": [
        "https://pub-c17bac2473334bf1a31be4c8877715fc.r2.dev/games/progressbar95-ss0.webp",
        "https://pub-c17bac2473334bf1a31be4c8877715fc.r2.dev/games/progressbar95-ss1.webp",
        "https://pub-c17bac2473334bf1a31be4c8877715fc.r2.dev/games/progressbar95-ss2.webp"
      ]
    }
  },
  {
    "slug": "bright-side-riddles-and-puzzles",
    "content": "ব্রাইট সাইড: রিডলস অ্যান্ড পাজলস'-এ আপনাকে স্বাগতম, এমন একটি গেম যেখানে প্রতিটি চ্যালেঞ্জই আপনার পূর্ণ সম্ভাবনাকে উন্মোচন করার একটি পদক্ষেপ। এই গেমটি আপনার সমস্যা সমাধানের দক্ষতা পরীক্ষা করতে এবং আপনার কল্পনার সীমানাকে প্রসারিত করার জন্য ডিজাইন করা হয়েছে।\n\nএকটি প্রাণবন্ত, সদা পরিবর্তনশীল জগতে স্থাপিত, 'ব্রাইট সাইড: রিডলস অ্যান্ড পাজলস' খেলোয়াড়দের ক্রমবর্ধমান জটিল ধাঁধা এবং রহস্যের একটি সিরিজ অন্বেষণ করার জন্য আমন্ত্রণ জানায়। প্রতিটি লেভেল যুক্তি, সৃজনশীলতা এবং কৌশলের একটি অনন্য মিশ্রণ প্রদানের জন্য তৈরি করা হয়েছে, যা নিশ্চিত করে যে কোনো দুটি চ্যালেঞ্জ একই রকম মনে হবে না।\n\n## মূল বৈশিষ্ট্য\n\n### বিভিন্ন ধরণের পাজল\nক্লাসিক ধাঁধা থেকে শুরু করে আধুনিক লজিক পাজল পর্যন্ত, 'ব্রাইট সাইড' আপনাকে ব্যস্ত রাখতে বিভিন্ন ধরণের চ্যালেঞ্জ প্রদান করে।\n\n### ইন্টারেক্টিভ পরিবেশ\nএকটি গতিশীল, ইন্টারেক্টিভ জগতের মধ্যে পাজল সমাধান করুন যা আপনার প্রতিটি পদক্ষেপ এবং সিদ্ধান্তের প্রতি প্রতিক্রিয়া দেখায়।\n\n### ক্রমবর্ধমান কঠিনতা\nসহজ পাজল দিয়ে শুরু করুন এবং গেমে অগ্রসর হওয়ার সাথে সাথে ধীরে ধীরে আরও জটিল চ্যালেঞ্জ মোকাবেলা করুন।\n\n### মাল্টিপ্লেয়ার মোড\nউত্তেজনাপূর্ণ মাল্টিপ্লেয়ার মোডে বন্ধুদের সাথে প্রতিযোগিতা করুন অথবা একসাথে পাজল সমাধান করুন।\n\n### শিক্ষাগত উপযোগিতা\nপ্রতিটি পাজল সমাধানের মাধ্যমে আপনার জ্ঞানীয় দক্ষতা বৃদ্ধি করুন এবং নতুন সমস্যা সমাধানের কৌশল শিখুন।\n\n### কাস্টমাইজযোগ্য অভিজ্ঞতা\nকাস্টমাইজযোগ্য ডিফিকাল্টি সেটিংস এবং ব্যক্তিগত পছন্দের মাধ্যমে আপনার গেমিং অভিজ্ঞতাকে নিজের মতো করে সাজিয়ে নিন।\n\n## গেমপ্লের সংক্ষিপ্ত বিবরণ\n\n'ব্রাইট সাইড: রিডলস অ্যান্ড পাজলস'-এ খেলোয়াড়দের সামনে এমন কিছু পাজল উপস্থাপন করা হয়, যেগুলোর জন্য যৌক্তিক চিন্তাভাবনা, সৃজনশীলতা এবং কখনও কখনও গতানুগতিক ধারার বাইরের যুক্তির প্রয়োজন হয়। প্রতিটি পাজল এমনভাবে ডিজাইন করা হয়েছে যা একই সাথে চ্যালেঞ্জিং এবং ফলপ্রসূ, এবং সমাধান করার পর একটি কৃতিত্বের অনুভূতি দেয়। গেমটিতে একটি প্রোগ্রেসন সিস্টেম রয়েছে যা আপনার অগ্রগতির সাথে সাথে নতুন লেভেল এবং পাজলের ধরন আনলক করে। আপনি একা খেলুন বা বন্ধুদের সাথে, 'ব্রাইট সাইড' একটি সমৃদ্ধ এবং নিমগ্ন পাজল-সমাধানের অভিজ্ঞতা প্রদান করে যা আপনাকে বারবার ফিরে আসতে উৎসাহিত করবে।",
    "frontmatter": {
      "title": "Bright Side: Riddles and Puzzles",
      "description": "ব্রাইট সাইড: রিডলস অ্যান্ড পাজলস'-এ ডুব দিন, একটি চিত্তাকর্ষক পাজল গেম যা আপনার বুদ্ধি এবং সৃজনশীলতার পরীক্ষা নেবে। ব্রেইন টিজার এবং লজিক গেমের অনুরাগীদের জন্য উপযুক্ত এই গেমটি সব বয়সের জন্য ঘন্টার পর ঘন্টা মজাদার বিনোদন দেবে।",
      "date": "2026-04-07",
      "category": "indie",
      "image": "https://pub-c17bac2473334bf1a31be4c8877715fc.r2.dev/games/bright-side-riddles-and-puzzles.webp",
      "game_name": "উজ্জ্বল দিক: ধাঁধা এবং পাজল",
      "developer": "MindCraft Studios",
      "publisher": "PuzzleWorks Interactive",
      "release_date": "১৫ সেপ্টেম্বর, ২০২৩",
      "download_url": "https://pixeldrain.com/u/LUXZ271X",
      "trailer_video_id": "",
      "genres": [
        "ক্যাজুয়াল",
        "ইন্ডি"
      ],
      "tags": [
        "ধাঁধা",
        "মস্তিষ্কের ধাঁধা",
        "যুক্তি",
        "পারিবারিক-বান্ধব",
        "শিক্ষামূলক"
      ],
      "platforms": [
        "Windows"
      ],
      "screenshots": [
        "https://pub-c17bac2473334bf1a31be4c8877715fc.r2.dev/games/bright-side-riddles-and-puzzles-ss0.webp",
        "https://pub-c17bac2473334bf1a31be4c8877715fc.r2.dev/games/bright-side-riddles-and-puzzles-ss1.webp",
        "https://pub-c17bac2473334bf1a31be4c8877715fc.r2.dev/games/bright-side-riddles-and-puzzles-ss2.webp"
      ]
    }
  },
  {
    "slug": "day-in-day-out",
    "content": "Day In Day Out-এ একজন সাধারণ মানুষের ভূমিকায় অবতীর্ণ হন, যিনি এক অসাধারণ জীবনযাপন করছেন। এই কাহিনী-নির্ভর লাইফ সিমুলেশন গেমটি আপনাকে দৈনন্দিন মুহূর্তগুলোর সৌন্দর্য অন্বেষণ করতে আমন্ত্রণ জানায়, যেখানে আপনার প্রতিটি সিদ্ধান্ত আপনার চরিত্রের যাত্রাকে প্রভাবিত করে।\n\nDay In Day Out আপনাকে একটি প্রাণবন্ত, জীবনঘনিষ্ঠ জগতে নিমজ্জিত করে, যেখানে আপনি সম্পর্ক তৈরি করবেন, শখ পূরণ করবেন এবং দৈনন্দিন জীবনের চ্যালেঞ্জগুলো মোকাবেলা করবেন। সকালের রুটিন থেকে শুরু করে গভীর রাতের কথোপকথন পর্যন্ত, গেমটি মানবিক সংযোগ এবং ব্যক্তিগত বিকাশের সারমর্ম তুলে ধরে। আপনার সিদ্ধান্তগুলোই গল্পকে রূপ দেয়, যা প্রতিটি প্লে-থ্রুকে অনন্য এবং গভীরভাবে ব্যক্তিগত করে তোলে।\n\n## মূল বৈশিষ্ট্য\n\n### গতিশীল গল্প বলার ধরণ\nএকটি শাখা-প্রশাখা যুক্ত কাহিনীর অভিজ্ঞতা নিন, যেখানে আপনার পছন্দগুলো বিভিন্ন পরিণতির দিকে নিয়ে যায়, যা নিশ্চিত করে যে দুটি প্লে-থ্রু কখনোই একরকম হবে না।\n\n### চরিত্রগুলোর সাথে গভীর মিথস্ক্রিয়া\nবিভিন্ন ধরনের চরিত্রের সাথে যুক্ত হন, যাদের প্রত্যেকের নিজস্ব ব্যক্তিত্ব, গল্প এবং বিকশিত সম্পর্ক রয়েছে।\n\n### ব্যক্তিগত দৈনন্দিন রুটিন\nআপনার চরিত্রের সময়সূচী, শখ এবং জীবনধারাকে নিজের মতো করে সাজিয়ে নিন, যাতে তাদের জীবন সম্পর্কে আপনার নিজস্ব দৃষ্টিভঙ্গি প্রতিফলিত হয়।\n\n### সুন্দরভাবে নির্মিত জগৎ\nমনোরম খুঁটিনাটি এবং লুকানো বিস্ময়ে ভরা, দৃষ্টিনন্দন ও হাতে গড়া এক পরিবেশ অন্বেষণ করুন।\n\n### অর্থবহ সিদ্ধান্ত\nএমন সব সিদ্ধান্ত নিন যা আপনার চরিত্রের কর্মজীবন, সম্পর্ক এবং সার্বিক সুখকে প্রভাবিত করবে এবং তাদের গল্পকে গভীর রূপ দেবে।\n\n## গেমপ্লের সংক্ষিপ্ত বিবরণ\nDay In Day Out জীবন সিমুলেশনের সাথে গল্পের গভীরতাকে একত্রিত করে, খেলোয়াড়দের তাদের চরিত্রের জীবন নিজেদের পছন্দমতো যাপন করার স্বাধীনতা দেয়। কাজ, সম্পর্ক এবং ব্যক্তিগত বিকাশের মধ্যে ভারসাম্য রেখে আপনার সময়কে বুদ্ধিমানের সাথে পরিচালনা করুন। গেমটির মূল মেকানিক্স সিদ্ধান্ত গ্রহণ, মিথস্ক্রিয়া এবং অন্বেষণের উপর কেন্দ্র করে তৈরি, যা একটি আরামদায়ক অথচ আকর্ষণীয় অভিজ্ঞতা প্রদান করে। আপনি স্বপ্নের কর্মজীবন গড়ার চেষ্টা করুন বা কেবল ছোট ছোট মুহূর্তগুলো উপভোগ করুন, Day In Day Out দৈনন্দিন জীবনের সৌন্দর্যকে উদযাপন করে।",
    "frontmatter": {
      "title": "Day In Day Out",
      "description": "Day In Day Out একটি হৃদয়স্পর্শী জীবন সিমুলেশন গেম, যেখানে আপনার সিদ্ধান্তগুলোই আপনার চরিত্রের গল্পকে গড়ে তোলে। অর্থপূর্ণ আলাপচারিতা ও সিদ্ধান্তে পরিপূর্ণ, সুন্দরভাবে নির্মিত একটি জগতে দৈনন্দিন জীবনের উত্থান-পতন অনুভব করুন।",
      "date": "2026-04-07",
      "category": "indie",
      "image": "https://pub-c17bac2473334bf1a31be4c8877715fc.r2.dev/games/day-in-day-out.webp",
      "game_name": "দিনরাত",
      "developer": "Lucid Dreams Studio",
      "publisher": "Evergreen Interactive",
      "release_date": "৭ জুলাই, ২০২৩",
      "download_url": "https://pixeldrain.com/u/DHUWLR1t",
      "trailer_video_id": "",
      "genres": [
        "ক্যাজুয়াল",
        "ইন্ডি"
      ],
      "tags": [
        "জীবন-অনুকরণ",
        "আখ্যান-নির্ভর",
        "সিদ্ধান্তের গুরুত্ব",
        "জীবনের খণ্ডচিত্র",
        "আরামদায়ক"
      ],
      "platforms": [
        "Windows"
      ],
      "screenshots": [
        "https://pub-c17bac2473334bf1a31be4c8877715fc.r2.dev/games/day-in-day-out-ss0.webp",
        "https://pub-c17bac2473334bf1a31be4c8877715fc.r2.dev/games/day-in-day-out-ss1.webp",
        "https://pub-c17bac2473334bf1a31be4c8877715fc.r2.dev/games/day-in-day-out-ss2.webp"
      ]
    }
  },
  {
    "slug": "a-little-to-the-left",
    "content": "এ লিটল টু দ্য লেফট' একটি অনন্য পাজল গেম যা দৈনন্দিন গোছানোর কাজকে একটি আনন্দদায়ক চ্যালেঞ্জে পরিণত করে। এর মিনিমালিস্ট ডিজাইন এবং শান্ত পরিবেশ খেলোয়াড়দের জীবনের অগোছালো বিষয়গুলোকে সৃজনশীলতা ও যত্নের সাথে মোকাবেলা করতে উৎসাহিত করে।\n\n'এ লিটল টু দ্য লেফট'-এ আপনি বিভিন্ন ধরনের গৃহস্থালির জিনিসপত্র এবং পরিস্থিতি পাবেন যা গোছানোর প্রয়োজন। শেলফে বই সাজানো থেকে শুরু করে ড্রয়ারে বাসনপত্র গোছানো পর্যন্ত, প্রতিটি পাজল পরিচিত কাজগুলোতে একটি নতুন মাত্রা যোগ করে। গেমটির হালকা রসিকতা এবং অপ্রত্যাশিত চমক খেলোয়াড়দের মগ্ন রাখে এবং মননশীলতা বাড়াতে উৎসাহিত করে।\n\n## মূল বৈশিষ্ট্য\n\n### সৃজনশীল পাজল\n১০০টিরও বেশি অনন্য পাজল সমাধান করুন যা আপনার উপলব্ধি এবং গোছানোর দক্ষতাকে চ্যালেঞ্জ করবে। প্রতিটি কাজ স্বজ্ঞাত মনে হলেও এটি একটি সন্তোষজনক মানসিক অনুশীলন প্রদান করে।\n\n### মিনিমালিস্ট ডিজাইন\nএকটি পরিচ্ছন্ন, দৃষ্টিনন্দন আর্ট স্টাইল উপভোগ করুন যা সরলতা এবং স্বচ্ছতার উপর জোর দেয়। গেমটির নান্দনিকতা এর শান্ত পরিবেশকে আরও বাড়িয়ে তোলে।\n\n### আরামদায়ক গেমপ্লে\nচাপমুক্ত থাকার জন্য ডিজাইন করা, 'এ লিটল টু দ্য লেফট' খেলোয়াড়দের সময় নিয়ে গোছানোর প্রক্রিয়াটি উপভোগ করতে উৎসাহিত করে।\n\n### নির্মল হাস্যরস\nখেলোয়াড়সুলভ মুহূর্ত এবং অপ্রত্যাশিত মোড় আবিষ্কার করুন যা অভিজ্ঞতায় আকর্ষণ ও স্বকীয়তা যোগ করে।\n\n### বারবার খেলার যোগ্য চ্যালেঞ্জ\nঅনেক পাজলের একাধিক সমাধান রয়েছে, যা পরীক্ষা-নিরীক্ষা এবং বারবার খেলার সুযোগকে উৎসাহিত করে।\n\n## গেমপ্লের সংক্ষিপ্ত বিবরণ\n'এ লিটল টু দ্য লেফট' স্বতঃস্ফূর্ত মিথস্ক্রিয়া এবং সৃজনশীল সমস্যা সমাধানের উপর মনোযোগ দেয়। খেলোয়াড়রা প্রতিটি দৃশ্যে সামঞ্জস্য আনার জন্য বস্তুগুলোকে টেনে, ঘুরিয়ে এবং সাজিয়ে নেয়। গেমটির ধীর গতি এবং টাইমারের অনুপস্থিতি এটিকে সব স্তরের খেলোয়াড়দের জন্য সহজলভ্য করে তোলে। আপনি পাজলপ্রেমী হোন বা শুধু একটি শান্তিময় মুক্তি খুঁজুন, 'এ লিটল টু দ্য লেফট' একটি অনন্য সন্তোষজনক অভিজ্ঞতা প্রদান করে।",
    "frontmatter": {
      "title": "A Little to the Left",
      "description": "A Little to the Left হলো দৈনন্দিন জিনিসপত্র গোছানোর একটি চমৎকার পাজল গেম। সৃজনশীল চ্যালেঞ্জ সমাধান করুন, বিশৃঙ্খলাকে মেনে নিন এবং গুছিয়ে রাখার মধ্যে সন্তুষ্টি খুঁজে নিন। শান্ত ও সরল গেমপ্লের অনুরাগীদের জন্য এটি একদম উপযুক্ত।",
      "date": "2026-04-07",
      "category": "indie",
      "image": "https://pub-c17bac2473334bf1a31be4c8877715fc.r2.dev/games/a-little-to-the-left.webp",
      "game_name": "একটু বামে",
      "developer": "Max Inferno",
      "publisher": "Secret Mode",
      "release_date": "৮ নভেম্বর, ২০২২",
      "download_url": "https://pixeldrain.com/u/HJczNz8V",
      "trailer_video_id": "",
      "metacritic": 75.0,
      "genres": [
        "ক্যাজুয়াল",
        "ইন্ডি"
      ],
      "tags": [
        "ধাঁধা",
        "আরামদায়ক",
        "সংগঠন",
        "ইন্ডি",
        "স্বাস্থ্যকর"
      ],
      "platforms": [
        "Windows",
        "Mac"
      ],
      "screenshots": [
        "https://pub-c17bac2473334bf1a31be4c8877715fc.r2.dev/games/a-little-to-the-left-ss0.webp",
        "https://pub-c17bac2473334bf1a31be4c8877715fc.r2.dev/games/a-little-to-the-left-ss1.webp",
        "https://pub-c17bac2473334bf1a31be4c8877715fc.r2.dev/games/a-little-to-the-left-ss2.webp"
      ]
    }
  },
  {
    "slug": "wallpaper-engine",
    "content": "ওয়ালপেপার ইঞ্জিন প্রাণবন্ত অ্যানিমেটেড এবং ইন্টারেক্টিভ ওয়ালপেপারের মাধ্যমে আপনার ডেস্কটপের অভিজ্ঞতাকে উন্নত করে। সৃজনশীলতা এবং ব্যক্তিগতকরণের জন্য ডিজাইন করা একটি টুলের সাহায্যে আপনার স্ক্রিনকে জীবন্ত করে তুলুন।\n\nওয়ালপেপার ইঞ্জিনে রয়েছে ওয়ালপেপারের এক বিশাল লাইব্রেরি, যেখানে শান্ত প্রাকৃতিক দৃশ্য থেকে শুরু করে প্রাণবন্ত অ্যানিমেশন পর্যন্ত সবকিছুই আছে। আপনি মৃদু গতি বা সম্পূর্ণ ইন্টারেক্টিভ দৃশ্য যা-ই পছন্দ করুন না কেন, এই প্ল্যাটফর্মটি আপনাকে আপনার ডেস্কটপকে এমনভাবে কাস্টমাইজ করার সুযোগ দেয় যা আগে কখনও সম্ভব ছিল না। 2D, 3D, এবং ভিডিও ওয়ালপেপারের সাপোর্টের মাধ্যমে ওয়ালপেপার ইঞ্জিন নিশ্চিত করে যে আপনার স্ক্রিন আপনার স্টাইলকেই প্রতিফলিত করবে।\n\n## মূল বৈশিষ্ট্য\n\n### অফুরন্ত কাস্টমাইজেশন\nহাজার হাজার ওয়ালপেপার থেকে বেছে নিন অথবা বিল্ট-ইন টুল ব্যবহার করে নিজের ওয়ালপেপার তৈরি করুন। আপনার মেজাজ বা পছন্দের সাথে মিলিয়ে ডেস্কটপকে সাজিয়ে নিন।\n\n### ইন্টারেক্টিভ ওয়ালপেপার\nএমন ওয়ালপেপারের অভিজ্ঞতা নিন যা আপনার মাউসের নড়াচড়া বা সিস্টেমের পারফরম্যান্সের সাথে সাড়া দেয়, যা আপনার ডেস্কটপে একটি গতিশীল মাত্রা যোগ করে।\n\n### মাল্টি-মনিটর সাপোর্ট\nএকটি সামঞ্জস্যপূর্ণ এবং নিমগ্ন ভিজ্যুয়াল অভিজ্ঞতার জন্য একাধিক স্ক্রিন জুড়ে নির্বিঘ্নে ওয়ালপেপার প্রসারিত করুন।\n\n### রিসোর্স দক্ষতা\nওয়ালপেপার ইঞ্জিন ব্যাকগ্রাউন্ডে মসৃণভাবে চলে, যা চমৎকার ভিজ্যুয়াল প্রদানের পাশাপাশি সিস্টেম পারফরম্যান্সের উপর ন্যূনতম প্রভাব নিশ্চিত করে।\n\n### ওয়ার্কশপ ইন্টিগ্রেশন\nব্যবহারকারীদের তৈরি কন্টেন্ট ডাউনলোড করতে অথবা আপনার সৃষ্টিগুলো বিশ্বব্যাপী কমিউনিটির সাথে শেয়ার করতে স্টিম ওয়ার্কশপ অ্যাক্সেস করুন।\n\n## গেমপ্লে ওভারভিউ\nওয়ালপেপার ইঞ্জিন শুধু একটি টুল নয়—এটি সৃজনশীলতার একটি প্রবেশদ্বার। ব্যবহারকারীরা রিয়েল-টাইমে ওয়ালপেপারগুলো অন্বেষণ, কাস্টমাইজ এবং সেগুলোর সাথে ইন্টারঅ্যাক্ট করতে পারেন। প্ল্যাটফর্মটি 2D অ্যানিমেশন, 3D সিন এবং ভিডিও ফাইলসহ বিভিন্ন ফরম্যাট সাপোর্ট করে, যা অফুরন্ত সম্ভাবনা নিশ্চিত করে। আপনি একজন সাধারণ ব্যবহারকারী বা নির্মাতা, যাই হোন না কেন, ওয়ালপেপার ইঞ্জিন আপনার ডিজিটাল স্পেসকে ব্যক্তিগত রূপ দেওয়ার একটি অনন্য উপায় প্রদান করে।",
    "frontmatter": {
      "title": "Wallpaper Engine",
      "description": "ওয়ালপেপার ইঞ্জিন একটি গতিশীল ডেস্কটপ কাস্টমাইজেশন টুল যা চমৎকার অ্যানিমেটেড এবং ইন্টারেক্টিভ ওয়ালপেপার দিয়ে আপনার স্ক্রিনকে রূপান্তরিত করে। এই অনন্য ওয়ালপেপার ইঞ্জিনের সাহায্যে অফুরন্ত সৃজনশীলতা অন্বেষণ করুন।",
      "date": "2026-04-07",
      "category": "indie",
      "image": "https://pub-c17bac2473334bf1a31be4c8877715fc.r2.dev/games/wallpaper-engine.webp",
      "game_name": "ওয়ালপেপার ইঞ্জিন",
      "developer": "Kristjan Skutta",
      "publisher": "Wallpaper Engine Team",
      "release_date": "১৬ নভেম্বর, ২০১৮",
      "download_url": "https://pixeldrain.com/u/SvXudcTH",
      "trailer_video_id": "",
      "genres": [
        "ক্যাজুয়াল",
        "ইন্ডি",
        "অ্যানিমেশন ও মডেলিং",
        "ডিজাইন ও ইলাস্ট্রেশন",
        "ফটো এডিটিং",
        "ইউটিলিটিস"
      ],
      "tags": [
        "কাস্টমাইজেশন",
        "ওয়ালপেপার",
        "অ্যানিমেটেড",
        "ইন্টারেক্টিভ",
        "মাল্টিমিডিয়া"
      ],
      "platforms": [
        "Windows"
      ],
      "screenshots": [
        "https://pub-c17bac2473334bf1a31be4c8877715fc.r2.dev/games/wallpaper-engine-ss0.webp",
        "https://pub-c17bac2473334bf1a31be4c8877715fc.r2.dev/games/wallpaper-engine-ss1.webp",
        "https://pub-c17bac2473334bf1a31be4c8877715fc.r2.dev/games/wallpaper-engine-ss2.webp"
      ]
    }
  },
  {
    "slug": "you-died-but-a-necromancer-revived-you",
    "content": "You Died but a Necromancer revived you' গেমটিতে, খেলোয়াড়দের এমন এক জগতে ঠেলে দেওয়া হয় যেখানে মৃত্যু কোনো শেষ নয়, বরং এক ভুতুড়ে যাত্রার শুরু। একজন শক্তিশালী নেক্রোম্যান্সারের দ্বারা পুনরুজ্জীবিত এক পতিত যোদ্ধা হিসেবে, আপনাকে বিপদ ও রহস্যে ভরা এক অন্ধকার ও জটিল ফ্যান্টাসি জগতে পথ চলতে হবে।\n\nএই গেমটি তীব্র অ্যাকশন আরপিজি মেকানিক্সের সাথে একটি আকর্ষণীয় কাহিনিকে একত্রিত করেছে। এক বিশাল উন্মুক্ত বিশ্বে, আপনি অভিশপ্ত ভূমি অন্বেষণ করবেন, দানবীয় প্রাণীদের সাথে যুদ্ধ করবেন এবং আপনার পুনরুজ্জীবনের পেছনের সত্য উন্মোচন করবেন। যে নেক্রোম্যান্সার আপনাকে পুনরুজ্জীবিত করেছে, তার কাছে এমন গোপন রহস্য রয়েছে যা বিশ্বের ভাগ্য পরিবর্তন করতে পারে, এবং আপনার সিদ্ধান্তই এর ফলাফল নির্ধারণ করবে।\n\n## মূল বৈশিষ্ট্য\n\n### গতিশীল নেক্রোম্যান্সি শক্তি\nমৃত মিত্রদের ডেকে আনতে, অন্ধকার শক্তিকে নিয়ন্ত্রণ করতে এবং যুদ্ধের মোড় ঘুরিয়ে দিতে নেক্রোম্যান্সির শক্তিকে কাজে লাগান।\n\n### বিশাল উন্মুক্ত বিশ্ব\nঅন্ধকার জঙ্গল, প্রাচীন ধ্বংসাবশেষ এবং ভুতুড়ে গ্রামে ভরা এক সমৃদ্ধ ও বিস্তারিত বিশ্ব অন্বেষণ করুন, যার প্রতিটির নিজস্ব গোপন রহস্য এবং চ্যালেঞ্জ রয়েছে।\n\n### চরিত্রের গভীর কাস্টমাইজেশন\nআপনার চরিত্রের ক্ষমতা, চেহারা এবং খেলার ধরণ নিজের পছন্দ অনুযায়ী সাজিয়ে নিন।\n\n### নৈতিক সিদ্ধান্ত\nগুরুত্বপূর্ণ সিদ্ধান্ত নিন যা গল্প, এনপিসিদের (NPCs) সাথে আপনার সম্পর্ক এবং আপনার চারপাশের বিশ্বকে প্রভাবিত করবে।\n\n### তীব্র যুদ্ধ ব্যবস্থা\nদ্রুতগতির, দক্ষতা-ভিত্তিক যুদ্ধে অংশ নিন যা হাতাহাতি, জাদু এবং কৌশলগত নেক্রোম্যান্সির সমন্বয়ে গঠিত।\n\n## গেমপ্লের সংক্ষিপ্ত বিবরণ\n\n'You Died but a Necromancer revived you' গেমে খেলোয়াড়রা অন্বেষণ, যুদ্ধ এবং গল্প বলার এক মিশ্রণের অভিজ্ঞতা লাভ করবে। এর মূল মেকানিক্স নেক্রোম্যান্সির শক্তি ব্যবহার করে ধাঁধা সমাধান, শত্রুদের পরাজিত করা এবং গেমের জগতে পথ খুঁজে বের করার উপর ভিত্তি করে তৈরি। গেমটির অনন্য পুনরুত্থান কৌশল আপনাকে সৃজনশীল উপায়ে মৃত্যুকে ফাঁকি দেওয়ার সুযোগ দেয়, যা যুদ্ধ এবং অন্বেষণ উভয় ক্ষেত্রেই গভীরতা যোগ করে। নেক্রোম্যান্সারের উদ্দেশ্য এবং আপনি এখন যে অভিশপ্ত ভূমিতে বাস করছেন তার রহস্য উন্মোচন করার সাথে সাথে একটি চ্যালেঞ্জিং কিন্তু ফলপ্রসূ অভিজ্ঞতার জন্য প্রস্তুত থাকুন।",
    "frontmatter": {
      "title": "You Died but a Necromancer revived you",
      "description": "You Died but a Necromancer revived you'-তে এমন এক ডার্ক ফ্যান্টাসি আরপিজি-কে আলিঙ্গন করুন, যেখানে মৃত্যু কেবলই শুরু। এক রহস্যময় নেক্রোম্যান্সারের সাথে আবদ্ধ এক পুনরুজ্জীবিত যোদ্ধা হিসেবে খেলুন এবং এক অভিশপ্ত ভূমির গোপন রহস্য উন্মোচন করুন।",
      "date": "2026-04-07",
      "category": "indie",
      "image": "https://pub-c17bac2473334bf1a31be4c8877715fc.r2.dev/games/you-died-but-a-necromancer-revived-you.webp",
      "game_name": "তুমি মারা গিয়েছিলে কিন্তু একজন নেক্রোম্যান্সার তোমাকে পুনরুজ্জীবিত করেছে",
      "developer": "Ethereal Studios",
      "publisher": "Shadowplay Interactive",
      "release_date": "১৯ এপ্রিল, ২০১৯",
      "download_url": "https://pixeldrain.com/u/EgGw4o61",
      "trailer_video_id": "",
      "genres": [
        "ক্যাজুয়াল",
        "ইন্ডি"
      ],
      "tags": [
        "অ্যাকশন",
        "আরপিজি",
        "ডার্ক ফ্যান্টাসি",
        "নেক্রোম্যান্সি",
        "ওপেন ওয়ার্ল্ড"
      ],
      "platforms": [
        "Windows",
        "Linux"
      ],
      "screenshots": [
        "https://pub-c17bac2473334bf1a31be4c8877715fc.r2.dev/games/you-died-but-a-necromancer-revived-you-ss0.webp",
        "https://pub-c17bac2473334bf1a31be4c8877715fc.r2.dev/games/you-died-but-a-necromancer-revived-you-ss1.webp",
        "https://pub-c17bac2473334bf1a31be4c8877715fc.r2.dev/games/you-died-but-a-necromancer-revived-you-ss2.webp"
      ]
    }
  },
  {
    "slug": "muse-dash",
    "content": "মিউজ ড্যাশ রিদম গেমের রোমাঞ্চের সাথে সাইড-স্ক্রোলিং অ্যাকশনের উত্তেজনাকে একত্রিত করে। এক চোখধাঁধানো অ্যানিমে-অনুপ্রাণিত জগতে প্রবেশ করুন, যেখানে সঙ্গীত এবং যুদ্ধ একসাথে মিশে যায়।\n\nমিউজ ড্যাশে, আপনি একাধিক উদ্যমী নায়িকার মধ্যে একজনের ভূমিকায় খেলবেন, যাদের প্রত্যেকেরই রয়েছে নিজস্ব ক্ষমতা। শত্রু এবং বাধায় ভরা লেভেলগুলো আপনাকে দ্রুতগতিতে পার করতে হবে। গেমটি জে-পপ থেকে শুরু করে ইলেকট্রনিক পর্যন্ত বিভিন্ন ঘরানার উচ্চ-শক্তির ট্র্যাকের তালে আপনার কার্যকলাপকে সিঙ্ক করে। এর আকর্ষণীয় আর্ট স্টাইল এবং আসক্তিকর গেমপ্লের মাধ্যমে, মিউজ ড্যাশ রিদম গেম ঘরানায় একটি নতুন মাত্রা যোগ করেছে।\n\n## মূল বৈশিষ্ট্য\n\n### প্রাণবন্ত অ্যানিমে নান্দনিকতা\nমিউজ ড্যাশের রয়েছে একটি রঙিন, অ্যানিমে-অনুপ্রাণিত আর্ট স্টাইল, যেখানে আছে গতিশীল চরিত্রের ডিজাইন এবং প্রাণবন্ত ব্যাকগ্রাউন্ড যা সঙ্গীতের সাথে স্পন্দিত হয়।\n\n### ৩০০+ মিউজিক ট্র্যাক\nমূল কম্পোজিশন এবং লাইসেন্স করা ট্র্যাক সহ গানের এক বিশাল লাইব্রেরি উপভোগ করুন, যেখানে আপডেট এবং ডিএলসি-র মাধ্যমে নিয়মিত আরও গান যুক্ত করা হয়।\n\n### সহজ অথচ গভীর গেমপ্লে\nখেলা শুরু করা সহজ কিন্তু এতে দক্ষতা অর্জন করা কঠিন, Muse Dash একটি দুই-বাটন কন্ট্রোল স্কিম ব্যবহার করে যা খেলার অগ্রগতির সাথে সাথে আপনার ছন্দ এবং রিফ্লেক্সকে চ্যালেঞ্জ করে।\n\n### খেলার যোগ্য একাধিক চরিত্র\nএকাধিক নায়িকার তালিকা থেকে বেছে নিন, যাদের প্রত্যেকেরই রয়েছে অনন্য ক্ষমতা এবং খেলার ধরণ, যা আপনার খেলাকে বৈচিত্র্যময় করে তোলে এবং বারবার খেলার সুযোগ করে দেয়।\n\n### কাস্টমাইজযোগ্য অভিজ্ঞতা\nআপনার দক্ষতার স্তর অনুযায়ী অভিজ্ঞতাকে সাজিয়ে নিতে, কঠিনতার স্তর সামঞ্জস্য করুন, পোশাক আনলক করুন এবং বিভিন্ন মডিফায়ার ব্যবহার করে আপনার গেমপ্লেকে ব্যক্তিগত রূপ দিন।\n\n## গেমপ্লের সংক্ষিপ্ত বিবরণ\n\nMuse Dash-এর মূল মেকানিক্স একটি সাইড-স্ক্রোলিং পরিবেশে চলার সময় সঙ্গীতের সাথে তাল মিলিয়ে নোট হিট করার উপর ভিত্তি করে তৈরি। আপনি বিটের সাথে ট্যাপ, হোল্ড এবং স্লাইড করে শত্রুদের পরাজিত করবেন এবং বাধা এড়িয়ে চলবেন। গেমটি উচ্চ স্কোর এবং কম্বো দিয়ে নির্ভুলতার জন্য পুরস্কৃত করে, এবং এর ডাইনামিক স্টেজগুলো অ্যাকশনকে সতেজ রাখে। আপনি একজন সাধারণ খেলোয়াড় বা রিদম গেমের অভিজ্ঞ খেলোয়াড়, যাই হোন না কেন, Muse Dash সঙ্গীত এবং অ্যাকশনের একটি সন্তোষজনক মিশ্রণ প্রদান করে যা খেলা বন্ধ করা কঠিন করে তোলে।",
    "frontmatter": {
      "title": "Muse Dash",
      "description": "মিউজ ড্যাশ একটি প্রাণবন্ত রিদম-অ্যাকশন গেম, যেখানে আপনি রঙিন অ্যানিমে-স্টাইলের জগতে গানের তালে তালে ছুটে চলবেন। ৩০০টিরও বেশি লেভেলে রোমাঞ্চকর মিউজিক ট্র্যাকের সাথে ট্যাপ, স্লাইড এবং শত্রুদের গুঁড়িয়ে দিন। রিদম গেম ভক্তদের জন্য এটি একদম উপযুক্ত!",
      "date": "2026-04-07",
      "category": "indie",
      "image": "https://pub-c17bac2473334bf1a31be4c8877715fc.r2.dev/games/muse-dash.webp",
      "game_name": "মিউজ ড্যাশ",
      "developer": "PeroPeroGames",
      "publisher": "X.D. Network Inc.",
      "release_date": "১৯ জুন, ২০১৯",
      "download_url": "https://gofile.io/d/aalmYN",
      "trailer_video_id": "",
      "genres": [
        "অ্যাকশন",
        "ক্যাজুয়াল",
        "ইন্ডি"
      ],
      "tags": [
        "রিদম",
        "অ্যাকশন",
        "অ্যানিমে",
        "মিউজিক",
        "ক্যাজুয়াল"
      ],
      "platforms": [
        "Windows",
        "Mac"
      ],
      "screenshots": [
        "https://pub-c17bac2473334bf1a31be4c8877715fc.r2.dev/games/muse-dash-ss0.webp",
        "https://pub-c17bac2473334bf1a31be4c8877715fc.r2.dev/games/muse-dash-ss1.webp",
        "https://pub-c17bac2473334bf1a31be4c8877715fc.r2.dev/games/muse-dash-ss2.webp"
      ]
    }
  },
  {
    "slug": "incredibox",
    "content": "ইনক্রেডিবক্স একটি উদ্ভাবনী মিউজিক গেম যা আপনাকে আপনার নিজের ভার্চুয়াল ব্যান্ডের ডিজে হওয়ার সুযোগ দেয়। এর সহজ ড্র্যাগ-অ্যান্ড-ড্রপ ইন্টারফেসের মাধ্যমে, খেলোয়াড়রা বিভিন্ন সাউন্ড এলিমেন্ট একত্রিত করে আকর্ষণীয় সুর তৈরি করতে পারে।\n\n## মূল বৈশিষ্ট্য\n\n### ড্র্যাগ-অ্যান্ড-ড্রপ সাউন্ড ডিজাইন\nঅ্যানিমেটেড ক্যারেক্টারগুলোর উপর আইকন ড্র্যাগ করে সহজেই মিউজিক তৈরি করুন, প্রতিটি আইকন একটি ভিন্ন সাউন্ড বা বাদ্যযন্ত্রের প্রতিনিধিত্ব করে। এর সহজবোধ্য ইন্টারফেস এটিকে সব বয়সের জন্য সহজলভ্য করে তোলে।\n\n### একাধিক মিউজিক স্টাইল\nইনক্রেডিবক্সের বিভিন্ন সংস্করণে হিপ-হপ থেকে ইলেকট্রনিক পর্যন্ত বিভিন্ন মিউজিক্যাল জনরা এবং থিম অন্বেষণ করুন, যার প্রতিটির নিজস্ব সাউন্ড এবং ভিজ্যুয়াল রয়েছে।\n\n### আপনার সৃষ্টি শেয়ার করুন\nআপনার সৃজনশীলতা এবং অনন্য কম্পোজিশন প্রদর্শন করে, আপনার সেরা মিউজিক্যাল সৃষ্টিগুলো রেকর্ড করুন এবং বন্ধুদের বা ইনক্রেডিবক্স কমিউনিটির সাথে শেয়ার করুন।\n\n### লুকানো কন্টেন্ট আনলক করুন\nনির্দিষ্ট উপায়ে সাউন্ড একত্রিত করে গোপন সুর এবং অ্যানিমেশন আবিষ্কার করুন, যা গেমটিতে একটি নতুন চমক এবং বারবার খেলার সুযোগ যোগ করে।\n\n### পারিবারিক আনন্দ\nএর রঙিন ভিজ্যুয়াল এবং সহজে ব্যবহারযোগ্য মেকানিক্সের কারণে, ইনক্রেডিবক্স সব বয়সের খেলোয়াড়দের জন্য উপযুক্ত, যা এটিকে একটি চমৎকার পারিবারিক কার্যকলাপে পরিণত করে।\n\n## গেমপ্লের সংক্ষিপ্ত বিবরণ\n\nইনক্রেডিবক্স সঙ্গীত নিয়ে পরীক্ষা-নিরীক্ষা করার একটি মজাদার এবং আকর্ষণীয় উপায় প্রদান করে। খেলোয়াড়রা সাউন্ড আইকনগুলিকে ক্যারেক্টারদের উপর টেনে এনে সঙ্গীতের স্তর তৈরি করে, যা সুরেলা বা বিশৃঙ্খল ট্র্যাক তৈরি করে। গেমটি সৃজনশীলতা এবং অন্বেষণকে উৎসাহিত করে, কারণ বিভিন্ন সংমিশ্রণ অনন্য ফলাফল দেয়। আপনি সঙ্গীতে নতুন বা একজন অভিজ্ঞ সুরকার, যা-ই হোন না কেন, ইনক্রেডিবক্স অফুরন্ত আনন্দ এবং আবিষ্কারের সুযোগ দেয়। আপনার সৃষ্টি শেয়ার করার ক্ষমতা এটিকে একটি সামাজিক মাত্রা দেয়, যা বন্ধু এবং অনলাইন কমিউনিটিগুলোর মধ্যে এটিকে জনপ্রিয় করে তুলেছে।",
    "frontmatter": {
      "title": "Incredibox",
      "description": "ইনক্রেডিবক্স একটি অনন্য মিউজিক গেম, যেখানে খেলোয়াড়রা অ্যানিমেটেড চরিত্রগুলোর ওপর সাউন্ড আইকন টেনে এনে ফেলে নিজেদের বিট তৈরি করে। সঙ্গীতপ্রেমী এবং সৃজনশীল মনের মানুষদের জন্য উপযুক্ত এই ইন্টারেক্টিভ অভিজ্ঞতাটি ছন্দ, সৃজনশীলতা এবং মজার এক অপূর্ব মেলবন্ধন।",
      "date": "2026-04-07",
      "category": "indie",
      "image": "https://pub-c17bac2473334bf1a31be4c8877715fc.r2.dev/games/incredibox.webp",
      "game_name": "ইনক্রেডিবক্স",
      "developer": "So Far So Good",
      "publisher": "So Far So Good",
      "release_date": "৩০ এপ্রিল, ২০২১",
      "download_url": "https://pixeldrain.com/u/YdtjmyPU",
      "trailer_video_id": "",
      "genres": [
        "ক্যাজুয়াল",
        "ইন্ডি"
      ],
      "tags": [
        "সঙ্গীত",
        "ছন্দ",
        "সৃজনশীল",
        "ইন্টারেক্টিভ",
        "পারিবারিক-বান্ধব"
      ],
      "platforms": [
        "Windows",
        "Mac"
      ],
      "screenshots": [
        "https://pub-c17bac2473334bf1a31be4c8877715fc.r2.dev/games/incredibox-ss0.webp",
        "https://pub-c17bac2473334bf1a31be4c8877715fc.r2.dev/games/incredibox-ss1.webp",
        "https://pub-c17bac2473334bf1a31be4c8877715fc.r2.dev/games/incredibox-ss2.webp"
      ]
    }
  },
  {
    "slug": "teenage-mutant-ninja-turtles-shredders-revenge",
    "content": "*টিনেজ মিউট্যান্ট নিনজা টার্টলস: শ্রেডার’স রিভেঞ্জ*-এর সাথে আপনার প্রিয় নায়কদের জগতে প্রবেশ করুন, যা ৯০-এর দশকের ক্লাসিক আর্কেড বিট 'এম আপ গেমগুলোর প্রতি একটি ভালোবাসার নিদর্শন। এই অ্যাকশন-প্যাকড গেমটি ছয়জন পর্যন্ত খেলোয়াড়ের জন্য নিয়ে এসেছে নস্টালজিক পিক্সেল আর্ট, বিস্ফোরক লড়াই এবং কাউচ কো-অপ বিশৃঙ্খলা।\n\nনিউ ইয়র্ক সিটি শ্রেডার এবং তার ফুট ক্ল্যানের দ্বারা অবরুদ্ধ, এবং শহরটিকে বাঁচানোর দায়িত্ব টার্টলদের—এপ্রিল ও'নিল এবং মাস্টার স্প্লিন্টারের মতো মিত্রদের সাথে নিয়ে। মূল কার্টুন এবং কমিকসের প্রতি শ্রদ্ধা রেখে, *শ্রেডার’স রিভেঞ্জ* পুরোনো ধাঁচের গেমপ্লের সাথে আধুনিকতার মিশ্রণ ঘটিয়েছে, যা ভক্ত এবং নতুন খেলোয়াড় উভয়ের জন্যই একটি নতুন অথচ পরিচিত অভিজ্ঞতা প্রদান করে।\n\n## মূল বৈশিষ্ট্য\n\n### ক্লাসিক বিট 'এম আপ অ্যাকশন\nসাবলীল লড়াই, কম্বো সিস্টেম এবং স্ক্রিন-ক্লিয়ারিং স্পেশাল মুভসের মাধ্যমে আর্কেড ব্রলার গেমের সোনালী যুগকে পুনরায় উপভোগ করুন, যা এই জনরার মূল ঐতিহ্যের প্রতি বিশ্বস্ত থাকে।\n\n### ছয়-খেলোয়াড়ের কো-অপ\nস্থানীয়ভাবে বা অনলাইনে বন্ধুদের সাথে মিলে একটি বিশাল ছয়-খেলোয়াড়ের মোডে যোগ দিন, যা TMNT গেমিং ইতিহাসের বৃহত্তম, এবং কচ্ছপদের শক্তিতে চালিত এক বিশৃঙ্খল তাণ্ডবের অভিজ্ঞতা নিন।\n\n### রেট্রো পিক্সেল আর্ট স্টাইল\nপ্রাণবন্ত পিক্সেল আর্ট এবং অ্যানিমেশনগুলো ৮০ ও ৯০-এর দশকের জনপ্রিয় TMNT নান্দনিকতার মূল নির্যাসকে ধারণ করে, সাথে রয়েছে কার্টুনের আইকনিক কণ্ঠশিল্পীরা।\n\n### বিস্তৃত মুভসেট\nপ্রতিটি টার্টলের নিজস্ব ক্ষমতা এবং কম্বো রয়েছে, যা খেলোয়াড়দের তাদের প্রিয় নায়কের লড়াইয়ের শৈলী আয়ত্ত করতে উৎসাহিত করে, যাতে সর্বোচ্চ রোমাঞ্চকর অ্যাকশন উপভোগ করা যায়।\n\n### নস্টালজিক সাউন্ডট্র্যাক\nটি লোপেস (*সোনিক ম্যানিয়া*) দ্বারা তৈরি একটি জোরালো মৌলিক সাউন্ডট্র্যাক রেট্রো সিন্থ বিটের সাথে আধুনিক শক্তির মিশ্রণ ঘটায়, যা গেমের পরিবেশের সাথে পুরোপুরি মানানসই।\n\n## গেমপ্লের সংক্ষিপ্ত বিবরণ\n\n*টিনেজ মিউট্যান্ট নিনজা টার্টলস: শ্রেডার’স রিভেঞ্জ* একটি দ্রুতগতির, সাইড-স্ক্রোলিং কমব্যাট প্রদান করে যেখানে খেলোয়াড়রা ফুট ক্ল্যান শত্রুদের ঢেউয়ের মধ্য দিয়ে ঘুষি, লাথি এবং ফ্লিপ করে এগিয়ে যায়। গেমটি ডজিং এবং সুপার মিটারের মতো নতুন মেকানিক্স যুক্ত করে ক্লাসিক ফর্মুলায় গভীরতা এনেছে। একাধিক ডিফিকাল্টি লেভেল, লুকানো সংগ্রহযোগ্য জিনিস এবং আনলকযোগ্য কন্টেন্ট থাকায় এটি একক খেলোয়াড় এবং দলবদ্ধ খেলোয়াড়দের জন্য বারবার খেলার সুযোগ করে দেয়। আপনি শৈশবের স্মৃতি রোমন্থন করুন বা প্রথমবারের মতো টার্টলদের আবিষ্কার করুন, এই গেমটি আপনাকে দারুণ এক সময় উপহার দেবে।",
    "frontmatter": {
      "title": "Teenage Mutant Ninja Turtles: Shredder’s Revenge",
      "description": "Teenage Mutant Ninja Turtles: Shredder’s Revenge একটি রোমাঞ্চকর বিট 'এম আপ গেম যা ক্লাসিক আর্কেড অ্যাকশন ফিরিয়ে আনে। এই পিক্সেল-পারফেক্ট রেট্রো অ্যাডভেঞ্চারে লিওনার্দো, মাইকেলঅ্যাঞ্জেলো, ডোনাটেলো এবং রাফায়েলের সাথে শ্রেডার ও ফুট ক্ল্যানের বিরুদ্ধে লড়াইয়ে যোগ দিন।",
      "date": "2026-04-07",
      "category": "indie",
      "image": "https://pub-c17bac2473334bf1a31be4c8877715fc.r2.dev/games/teenage-mutant-ninja-turtles-shredders-revenge.webp",
      "game_name": "টিনেজ মিউট্যান্ট নিনজা টার্টলস: শ্রেডারের প্রতিশোধ",
      "developer": "Tribute Games",
      "publisher": "Dotemu",
      "release_date": "১৬ জুন, ২০২২",
      "download_url": "https://pixeldrain.com/u/HAJFRPHz",
      "trailer_video_id": "",
      "metacritic": 84.0,
      "genres": [
        "অ্যাকশন",
        "অ্যাডভেঞ্চার",
        "ক্যাজুয়াল",
        "ইন্ডি"
      ],
      "tags": [
        "বিট 'এম আপ",
        "কো-অপ",
        "রেট্রো",
        "আর্কেড",
        "অ্যাকশন"
      ],
      "platforms": [
        "Windows",
        "Linux"
      ],
      "screenshots": [
        "https://pub-c17bac2473334bf1a31be4c8877715fc.r2.dev/games/teenage-mutant-ninja-turtles-shredders-revenge-ss0.webp",
        "https://pub-c17bac2473334bf1a31be4c8877715fc.r2.dev/games/teenage-mutant-ninja-turtles-shredders-revenge-ss1.webp",
        "https://pub-c17bac2473334bf1a31be4c8877715fc.r2.dev/games/teenage-mutant-ninja-turtles-shredders-revenge-ss2.webp"
      ]
    }
  },
  {
    "slug": "sanabi",
    "content": "SANABI-তে একজন অবসরপ্রাপ্ত সৈনিকের ভূমিকায় অবতীর্ণ হন, এটি একটি দৃষ্টিনন্দন অ্যাকশন-প্ল্যাটফর্মার যা তীব্র লড়াই এবং একটি আকর্ষণীয় কাহিনির মিশ্রণ ঘটায়। এই সাইবারপাঙ্ক অ্যাডভেঞ্চারটি আপনার রিফ্লেক্স পরীক্ষা করবে এবং আপনাকে এর ডিস্টোপিয়ান জগতে টেনে নিয়ে যাবে।\n\nSANABI-এর প্রেক্ষাপট একটি ভবিষ্যৎ শহর, যেখানে দুর্নীতি গভীরভাবে প্রোথিত। একটি শক্তিশালী যান্ত্রিক হাত সজ্জিত প্রাক্তন সৈনিক হিসেবে, আপনাকে একটি ভয়ংকর ষড়যন্ত্রের পেছনের সত্য উদঘাটন করতে আকাশচুম্বী অট্টালিকা এবং অন্ধকার গলিপথ পাড়ি দিতে হবে। গেমটির সাবলীল মুভমেন্ট সিস্টেম এবং চ্যালেঞ্জিং শত্রুরা প্রতিটি লড়াইকে একটি রোমাঞ্চকর অভিজ্ঞতায় পরিণত করে।\n\n## মূল বৈশিষ্ট্য\n\n### সাবলীল মুভমেন্ট মেকানিক্স\nআপনার যান্ত্রিক হাত ব্যবহার করে নির্ভুলভাবে দোল খান, ড্যাশ করুন এবং আরোহণ করুন, একটি উল্লম্ব নগরীতে চলাচলের শিল্পে দক্ষতা অর্জন করুন।\n\n### নৃশংস কমব্যাট সিস্টেম\nদ্রুতগতির হাতাহাতি লড়াইয়ে অংশ নিন, শত্রুদের পরাস্ত করতে ঘুষি, গ্র্যাপল এবং পরিবেশগত আক্রমণের সমন্বয় করুন।\n\n### সাইবারপাঙ্ক আখ্যান\nঅত্যন্ত সুন্দরভাবে নির্মিত এক ডিস্টোপিয়ান জগতে ষড়যন্ত্র, বিশ্বাসঘাতকতা এবং নৈতিক দ্বিধায় ভরা এক গভীর গল্পের উন্মোচন করুন।\n\n### চোখ ধাঁধানো ভিজ্যুয়াল শৈলী\nপিক্সেল আর্ট এবং আধুনিক লাইটিং এফেক্টের এক অনন্য মিশ্রণের অভিজ্ঞতা নিন, যা নিয়ন-আলোয় ঝলমলে শহরটিকে জীবন্ত করে তোলে।\n\n### চ্যালেঞ্জিং বস ফাইট\nবিশাল যান্ত্রিক শত্রুদের বিরুদ্ধে আপনার দক্ষতা পরীক্ষা করুন, যাদের প্রত্যেককে পরাজিত করার জন্য প্রয়োজন স্বতন্ত্র কৌশল।\n\n## গেমপ্লের সংক্ষিপ্ত বিবরণ\n\nSANABI প্ল্যাটফর্মিং এবং কমব্যাটকে নিপুণভাবে একত্রিত করেছে, যা খেলোয়াড়দের সর্বোচ্চ কার্যকারিতার জন্য মুভমেন্ট এবং অ্যাটাকের সমন্বয় করতে উৎসাহিত করে। আপনার যান্ত্রিক হাতটি শুধু লড়াই করার জন্য নয় - এটি পরিবেশের মধ্যে চলাচলের জন্য আপনার প্রধান হাতিয়ার, যা আপনাকে ফাঁকের মধ্যে দিয়ে ঝুলে পার হতে, দেয়াল বেয়ে উঠতে এবং বিভিন্ন বস্তুর সাথে ইন্টারঅ্যাক্ট করতে সাহায্য করে। গেমটি ধীরে ধীরে নতুন মেকানিক্স এবং বিভিন্ন ধরণের শত্রুর সাথে পরিচয় করিয়ে দেয়, যা আপনার পুরো যাত্রাপথে অভিজ্ঞতাকে সতেজ রাখে। অ্যাকশন সিকোয়েন্সের মাঝে, আপনি NPC-দের সাথে কথা বলবেন এবং এমন কিছু সিদ্ধান্ত নেবেন যা গল্প এবং আপনার চরিত্রের বিকাশ উভয়কেই প্রভাবিত করবে।",
    "frontmatter": {
      "title": "SANABI",
      "description": "সানাবি একটি ডিস্টোপিয়ান সাইবারপাঙ্ক জগতে স্থাপিত একটি রোমাঞ্চকর অ্যাকশন-প্ল্যাটফর্মার। যান্ত্রিক হাতসহ একজন অবসরপ্রাপ্ত সৈনিকের ভূমিকায় খেলুন, যিনি একটি অন্ধকার ষড়যন্ত্র উন্মোচন করতে নিয়ন-আলোয় আলোকিত শহরগুলোর মধ্যে দিয়ে দোল খেতে খেতে এগিয়ে যান। দ্রুতগতির লড়াই এবং আকর্ষণীয় কাহিনী আপনার জন্য অপেক্ষা করছে!",
      "date": "2026-04-07",
      "category": "indie",
      "image": "https://pub-c17bac2473334bf1a31be4c8877715fc.r2.dev/games/sanabi.webp",
      "game_name": "সানাবি",
      "developer": "WONDER POTION",
      "publisher": "NEOWIZ",
      "release_date": "৮ নভেম্বর, ২০২৩",
      "download_url": "https://gofile.io/d/z1GYTN",
      "trailer_video_id": "",
      "genres": [
        "অ্যাকশন",
        "অ্যাডভেঞ্চার",
        "ইন্ডি"
      ],
      "tags": [
        "অ্যাকশন",
        "অ্যাডভেঞ্চার",
        "প্ল্যাটফর্মার",
        "সাইবারপাঙ্ক",
        "সিঙ্গেলপ্লেয়ার"
      ],
      "platforms": [
        "Windows"
      ],
      "screenshots": [
        "https://pub-c17bac2473334bf1a31be4c8877715fc.r2.dev/games/sanabi-ss0.webp",
        "https://pub-c17bac2473334bf1a31be4c8877715fc.r2.dev/games/sanabi-ss1.webp",
        "https://pub-c17bac2473334bf1a31be4c8877715fc.r2.dev/games/sanabi-ss2.webp"
      ]
    }
  }
]